<?xml version="1.0" encoding="utf-8" ?>
<dwsync>
<file name="stylish-portfolio.css" server="ssh.magnusandreasen.com" local="131876358513666599" remote="131879269460000000" Dst="1" />
<file name="stylish-portfolio.scss" server="ssh.magnusandreasen.com" local="131810763720000000" remote="131879269460000000" Dst="1" />
<file name="_bootstrap-overrides.scss" server="ssh.magnusandreasen.com" local="131810763720000000" remote="131879269460000000" Dst="1" />
<file name="_callout.scss" server="ssh.magnusandreasen.com" local="131810763720000000" remote="131879269460000000" Dst="1" />
<file name="_footer.scss" server="ssh.magnusandreasen.com" local="131810763720000000" remote="131879269470000000" Dst="1" />
<file name="_global.scss" server="ssh.magnusandreasen.com" local="131810763720000000" remote="131879269470000000" Dst="1" />
<file name="_masthead.scss" server="ssh.magnusandreasen.com" local="131810763720000000" remote="131879269470000000" Dst="1" />
<file name="_mixins.scss" server="ssh.magnusandreasen.com" local="131810763720000000" remote="131879269470000000" Dst="1" />
<file name="_portfolio.scss" server="ssh.magnusandreasen.com" local="131810763720000000" remote="131879269470000000" Dst="1" />
<file name="_services.scss" server="ssh.magnusandreasen.com" local="131810763720000000" remote="131879269470000000" Dst="1" />
<file name="_sidebar.scss" server="ssh.magnusandreasen.com" local="131810763720000000" remote="131879269470000000" Dst="1" />
<file name="_variables.scss" server="ssh.magnusandreasen.com" local="131810763720000000" remote="131879269470000000" Dst="1" />
<file name="stylish-portfolio.css" server="ftp.magnusandreasen.com//" local="131876358513666599" remote="131879243400000000" Dst="1" />
</dwsync>